app/__init__.py
app/appctx/__init__.py
app/appctx/websocket.py
app/core/__init__.py
app/entity/__init__.py
app/entity/client.py
app/entity/client_socket.py
app/entity/ingest_document.py
app/entity/prompt.py
app/entity/setup.py
app/entity/user.py
app/library/__init__.py
app/library/deepseek.py
app/library/groq.py
app/library/mistral.py
app/library/ollama.py
app/library/openai.py
app/library/setup.py
app/library/storage.py
app/library/wrapper.py
app/presentation/__init__.py
app/presentation/request.py
app/repositories/__init__.py
app/repositories/client.py
app/repositories/ingest_document.py
app/repositories/prompt.py
app/repositories/setup.py
app/repositories/socket_client.py
app/repositories/user.py
app/router/__init__.py
app/router/http.py
app/ucase/__init__.py
app/ucase/chat/__init__.py
app/ucase/chat/chat.py
app/ucase/chat/delete.py
app/ucase/chat/files.py
app/ucase/chat/history.py
app/ucase/chat/socket.py
app/ucase/client/__init__.py
app/ucase/client/client_delete.py
app/ucase/client/client_detail.py
app/ucase/client/client_list.py
app/ucase/client/client_upsert.py
app/ucase/client/socket.py
app/ucase/ingest/__init__.py
app/ucase/ingest/chroma.py
app/ucase/ingest/ingest_list.py
app/ucase/ingest/ingest_upload.py
app/ucase/llm/__init__.py
app/ucase/llm/llm.py
app/ucase/login/__init__.py
app/ucase/login/client.py
app/ucase/login/logout.py
app/ucase/login/password.py
app/ucase/prompt/__init__.py
app/ucase/prompt/prompt_delete.py
app/ucase/prompt/prompt_insert.py
app/ucase/prompt/prompt_list.py
app/ucase/prompt/prompt_set.py
app/ucase/setup/__init__.py
app/ucase/setup/delete_setup.py
app/ucase/setup/get_setup.py
app/ucase/setup/list_setup.py
app/ucase/setup/llm_setup.py
app/ucase/setup/retrieval_setup.py
app/ucase/user/__init__.py
app/ucase/user/user_delete.py
app/ucase/user/user_detail.py
app/ucase/user/user_list.py
app/ucase/user/user_upsert.py
ochabot-0.8.4.dist-info/LICENSE
ochabot-0.8.4.dist-info/METADATA
ochabot-0.8.4.dist-info/WHEEL
ochabot-0.8.4.dist-info/entry_points.txt
ochabot-0.8.4.dist-info/RECORD
