Metadata-Version: 2.3
Name: ochabot
Version: 0.8.4
Summary: Ochabot RAG Tools
Author: Sofyan Saputra
Author-email: meongbego@gmail.com
Requires-Python: >=3.10,<3.12
Classifier: Programming Language :: Python :: 3
Classifier: Programming Language :: Python :: 3.10
Classifier: Programming Language :: Python :: 3.11
Requires-Dist: aiomysql (>=0.2.0,<0.3.0)
Requires-Dist: aioredis (>=2.0.1,<3.0.0)
Requires-Dist: aiosqlite (>=0.20.0,<0.21.0)
Requires-Dist: alembic (>=1.14.1,<2.0.0)
Requires-Dist: asyncpg (>=0.30.0,<0.31.0)
Requires-Dist: cryptography (>=44.0.0,<45.0.0)
Requires-Dist: environs (>=14.0.0,<15.0.0)
Requires-Dist: fastapi-pagination (>=0.12.14,<0.13.0)
Requires-Dist: greenlet (>=3.1.1,<4.0.0)
Requires-Dist: httpx (>=0.27.0,<0.28.0)
Requires-Dist: langchain (>=0.3.13,<0.4.0)
Requires-Dist: langchain-chroma (>=0.1.4,<0.2.0)
Requires-Dist: langchain-community (>=0.3.10,<0.4.0)
Requires-Dist: langchain-elasticsearch (>=0.3.1,<0.4.0)
Requires-Dist: langchain-groq (>=0.2.3,<0.3.0)
Requires-Dist: langchain-mistralai (>=0.2.4,<0.3.0)
Requires-Dist: langchain-nvidia-ai-endpoints (>=0.3.7,<0.4.0)
Requires-Dist: langchain-ollama (>=0.2.3,<0.3.0)
Requires-Dist: langchain-openai (>=0.3.0,<0.4.0)
Requires-Dist: langchain-redis (>=0.1.2,<0.2.0)
Requires-Dist: loguru (>=0.7.2,<0.8.0)
Requires-Dist: minio (>=7.2.15,<8.0.0)
Requires-Dist: motor (>=3.6.1,<4.0.0)
Requires-Dist: mysql-connector-python (>=9.1.0,<10.0.0)
Requires-Dist: numpy (<2.0)
Requires-Dist: openai (>=1.59.8,<2.0.0)
Requires-Dist: psycopg2 (>=2.9.10,<3.0.0)
Requires-Dist: pydantic (>=2.10.6,<3.0.0)
Requires-Dist: pyjwt (>=2.10.1,<3.0.0)
Requires-Dist: pymysql (>=1.1.1,<2.0.0)
Requires-Dist: pypdf (>=5.1.0,<6.0.0)
Requires-Dist: python-dotenv (>=1.0.1,<2.0.0)
Requires-Dist: python-json-logger (>=2.0.7,<3.0.0)
Requires-Dist: python-multipart (>=0.0.20,<0.0.21)
Requires-Dist: sqlalchemy (>=2.0.37,<3.0.0)
Requires-Dist: uvicorn (>=0.34.0,<0.35.0)
Requires-Dist: websockets (>=12.0,<13.0)
